README.md
setup.py
openssl_enc_compat/__init__.py
openssl_enc_compat/_version.py
openssl_enc_compat/cipher.py
openssl_enc_compat.egg-info/PKG-INFO
openssl_enc_compat.egg-info/SOURCES.txt
openssl_enc_compat.egg-info/dependency_links.txt
openssl_enc_compat.egg-info/top_level.txt