Metadata-Version: 2.1
Name: openssl-enc-compat
Version: 0.0.3
Summary: Pure Python read/write encryption/decryption of encrypted OpenSSL 1.1.1 files
Home-page: https://github.com/clach04/openssl_enc_compat
Author: clach04
License: UNKNOWN
Platform: any
Classifier: Development Status :: 4 - Beta
Classifier: License :: OSI Approved :: GNU Lesser General Public License v2 (LGPLv2)
Classifier: Operating System :: OS Independent
Classifier: Programming Language :: Python
Classifier: Programming Language :: Python :: 2
Classifier: Programming Language :: Python :: 2.7
Classifier: Programming Language :: Python :: 3
Classifier: Programming Language :: Python :: 3.8
Classifier: Programming Language :: Python :: 3.12
